cpf_utils/__init__.py
cpf_utils/cep.py
cpf_utils/cnpj.py
cpf_utils/formatter.py
cpf_utils/rg.py
cpf_utils/validator.py
cpf_utils_raul-1.1.1.dist-info/METADATA
cpf_utils_raul-1.1.1.dist-info/WHEEL
cpf_utils_raul-1.1.1.dist-info/top_level.txt
cpf_utils_raul-1.1.1.dist-info/RECORD
