Metadata-Version: 2.4
Name: cpf_utils-raul
Version: 1.1.1
Summary: Validação e formatação de documentos brasileiros (CPF, CNPJ, CEP, RG)
Home-page: https://github.com/seuusuario/cpf_utils
Author: Raul
Author-email: seu_email@example.com
License: MIT
Project-URL: Homepage, https://github.com/Rhot1963/cpf_utils-raul
Project-URL: Documentation, https://Rhot1963.github.io/cpf_utils-raul
Project-URL: Repository, https://github.com/Rhot1963/cpf_utils-raul
Requires-Python: >=3.8
Dynamic: author-email
Dynamic: home-page
